dbdocgen/__init__.py
dbdocgen-0.1.0.dist-info/METADATA
dbdocgen-0.1.0.dist-info/WHEEL
dbdocgen-0.1.0.dist-info/entry_points.txt
dbdocgen-0.1.0.dist-info/top_level.txt
dbdocgen-0.1.0.dist-info/RECORD
